cda_download/__init__.py
cda_download/helpers.py
cda_download/main.py
cda_download-0.0.9.dist-info/licenses/LICENSE
cda_download-0.0.9.dist-info/METADATA
cda_download-0.0.9.dist-info/WHEEL
cda_download-0.0.9.dist-info/top_level.txt
cda_download-0.0.9.dist-info/RECORD
